<?xml version="1.0" encoding="utf-8"?>
<Defs>
  <MusicExpanded.ThemeDef>
    <defName>ME_SH2</defName>
    <label>Music Expanded: Silent Hill 2</label>
    <description>Ambient and horror tracks from Silent Hill 2 integrated via Music Expanded Framework.</description>
    <iconPath>UI/Icons/SH2</iconPath>
    <tracks>
      <li>SH2_001</li>
      <li>SH2_002</li>
      <li>SH2_003</li>
      <li>SH2_004</li>
      <li>SH2_005</li>
      <li>SH2_006</li>
      <li>SH2_007</li>
      <li>SH2_008</li>
      <li>SH2_009</li>
      <li>SH2_010</li>
      <li>SH2_011</li>
      <li>SH2_012</li>
      <li>SH2_013</li>
      <li>SH2_014</li>
      <li>SH2_015</li>
      <li>SH2_016</li>
      <li>SH2_017</li>
      <li>SH2_018</li>
      <li>SH2_019</li>
      <li>SH2_020</li>
      <li>SH2_021</li>
      <li>SH2_022</li>
      <li>SH2_023</li>
      <li>SH2_024</li>
      <li>SH2_025</li>
      <li>SH2_026</li>
      <li>SH2_027</li>
      <li>SH2_028</li>
      <li>SH2_029</li>
      <li>SH2_030</li>
      <li>SH2_031</li>
      <li>SH2_032</li>
      <li>SH2_033</li>
      <li>SH2_034</li>
      <li>SH2_035</li>
      <li>SH2_036</li>
      <li>SH2_037</li>
      <li>SH2_038</li>
      <li>SH2_039</li>
      <li>SH2_040</li>
      <li>SH2_041</li>
      <li>SH2_042</li>
      <li>SH2_043</li>
      <li>SH2_044</li>
      <li>SH2_045</li>
      <li>SH2_046</li>
      <li>SH2_047</li>
      <li>SH2_048</li>
      <li>SH2_049</li>
      <li>SH2_050</li>
      <li>SH2_051</li>
      <li>SH2_052</li>
      <li>SH2_053</li>
      <li>SH2_054</li>
      <li>SH2_055</li>
      <li>SH2_056</li>
      <li>SH2_057</li>
      <li>SH2_058</li>
      <li>SH2_059</li>
      <li>SH2_060</li>
      <li>SH2_061</li>
      <li>SH2_062</li>
      <li>SH2_063</li>
      <li>SH2_064</li>
      <li>SH2_065</li>
      <li>SH2_066</li>
      <li>SH2_067</li>
      <li>SH2_068</li>
      <li>SH2_069</li>
      <li>SH2_070</li>
      <li>SH2_071</li>
      <li>SH2_072</li>
      <li>SH2_073</li>
    </tracks>
  </MusicExpanded.ThemeDef>
</Defs>
